MANIFEST.in
setup.cfg
setup.py
pycret_santa/__init__.py
pycret_santa/config.py
pycret_santa/config_test.py
pycret_santa/guests.py
pycret_santa/guests_test.py
pycret_santa/mails.py
pycret_santa/mails_test.py
pycret_santa/sample.yaml
pycret_santa/secret_santa.py
pycret_santa/secret_santa_test.py
pycret_santa/utils.py
pycret_santa.egg-info/PKG-INFO
pycret_santa.egg-info/SOURCES.txt
pycret_santa.egg-info/dependency_links.txt
pycret_santa.egg-info/entry_points.txt
pycret_santa.egg-info/requires.txt
pycret_santa.egg-info/top_level.txt