Metadata-Version: 1.1
Name: pycret-santa
Version: 0.3
Summary: Package that will help you organizing a Secret Santa party!
Home-page: https://github.com/RenaudParent/pycret-santa
Author: Renaud Parent
Author-email: renaud.parent@gmail.com
License: UNKNOWN
Download-URL: https://github.com/RenaudParent/pycret-santa/tarball/0.3
Keywords: secret,santa,christmas
Platform: UNKNOWN
